{
    "version": "0.3.3",
    "homepage": "https://t-sp.in/cambridge",
    "description": "Open source arcade stacker",
    "license": "MIT",
    "architecture": {
        "32bit": {
            "url": "https://github.com/MillaBasset/cambridge/releases/download/v0.3.3/cambridge-win32.zip",
            "hash": "daf1f2f1ec98ee5f3f02e1b4a2af4a51d1f8dc3efa40d653d7c69d1d86d84d64"
        },
        "64bit": {
            "url": "https://github.com/MillaBasset/cambridge/releases/download/v0.3.3/cambridge-windows.zip",
            "hash": "bfc1262fde045ea6e61c5c486f21f76f901d5cd54c1e1cbe30b256ea611f5182"
        }
    },
    "shortcuts": [
        [
            "cambridge.exe",
            "Cambridge"
        ]
    ],
    "checkver": {
        "github": "https://github.com/MillaBasset/cambridge"
    },
    "autoupdate": {
        "architecture": {
            "32bit": {
                "url": "https://github.com/MillaBasset/cambridge/releases/download/v$version/cambridge-win32.zip"
            },
            "64bit": {
                "url": "https://github.com/MillaBasset/cambridge/releases/download/v$version/cambridge-windows.zip"
            }
        }
    }
}
