{
    "homepage": "https://cataclysmdda.org",
    "description": "Turn-based survival game set in a post-apocalyptic world (with graphical tiles, experimental build)",
    "version": "9727",
    "license": "CC-BY-SA-3.0",
    "architecture": {
        "64bit": {
            "url": "https://github.com/CleverRaven/Cataclysm-DDA/releases/download/cdda-jenkins-b9727/cataclysmdda-0.D-Windows_x64-Tiles-9727.zip",
            "hash": "b47d786f1f13852781864c1d3922c071e978347115e1f5cc3a26e3c27744c32d"
        },
        "32bit": {
            "url": "https://github.com/CleverRaven/Cataclysm-DDA/releases/download/cdda-jenkins-b9727/cataclysmdda-0.D-Windows-Tiles-9727.zip",
            "hash": "fdf398e822477aed9bc1f301bece8e8718402ac0a0e36acca3a3b67f18056da0"
        }
    },
    "shortcuts": [
        [
            "cataclysm-tiles.exe",
            "Cataclysm DDA Tiles (Experimental)"
        ]
    ],
    "checkver": {
        "url": "https://github.com/CleverRaven/Cataclysm-DDA/releases/",
        "re": "Cataclysm-DDA experimental build #(.*)[<]"
    },
    "autoupdate": {
        "architecture": {
            "64bit": {
                "url": "https://github.com/CleverRaven/Cataclysm-DDA/releases/download/cdda-jenkins-b$version/cataclysmdda-0.D-Windows_x64-Tiles-$version.zip"
            },
            "32bit": {
                "url": "https://github.com/CleverRaven/Cataclysm-DDA/releases/download/cdda-jenkins-b$version/cataclysmdda-0.D-Windows-Tiles-$version.zip"
            }
        }
    }
}
