{
    "homepage": "http://www.eduke32.com/",
    "description": "Modern source port for Duke Nukem 3D",
    "version": "20181028-7138",
    "license": "http://www.eduke32.com/buildlic.txt",
    "architecture": {
        "64bit": {
            "url": "https://dukeworld.com/eduke32/synthesis/20181028-7138/eduke32_win64_20181028-7138.7z",
            "hash": "23c8437736de6962843896f6f312808d02cf82d52c9aebdd7e14bd1b5a33aa87"
        },
        "32bit": {
            "url": "https://dukeworld.com/eduke32/synthesis/20181028-7138/eduke32_win32_20181028-7138.7z",
            "hash": "fdc06260a1019b5f2862a09ba6440e5d5d523fc888177f30d1af3248f5e62ef6"
        }
    },
    "bin": [
        [
            "eduke32.exe",
            "eduke32",
            "-j $persist_dir\\data"
        ]
    ],
    "shortcuts": [
        [
            "eduke32.exe",
            "EDuke32",
            "-j data"
        ]
    ],
    "persist": [
        "data"
    ],
    "notes": [
        "Place GRP files (game data) in:",
        "",
        "\t$persist_dir\\data"
    ]
}
